[
  {
    "id": "8e7efe28-98e8-41ac-bf43-3aeac09efccf",
    "data": [
      {
        "text": "chair of career 360",
        "userDefined": false
      }
    ],
    "isTemplate": false,
    "count": 0,
    "updated": 1541513366
  },
  {
    "id": "eb9af6fd-e413-45b1-9d0c-5ea89aa5e29a",
    "data": [
      {
        "text": "Who is leading the career 360 track ?",
        "userDefined": false
      }
    ],
    "isTemplate": false,
    "count": 0,
    "updated": 1541188836
  },
  {
    "id": "0c79b150-9926-4718-9389-81b195dfc172",
    "data": [
      {
        "text": "Who ",
        "userDefined": false
      },
      {
        "text": "chairs",
        "alias": "Chair",
        "meta": "@Chair",
        "userDefined": false
      },
      {
        "text": " the career ",
        "userDefined": false
      },
      {
        "text": "360",
        "alias": "number",
        "meta": "@sys.number",
        "userDefined": false
      },
      {
        "text": " track ?",
        "userDefined": false
      }
    ],
    "isTemplate": false,
    "count": 0,
    "updated": 1541188836
  },
  {
    "id": "d7e813e7-f84b-4b5c-9c66-29a391ce505f",
    "data": [
      {
        "text": "Who leads the career ",
        "userDefined": false
      },
      {
        "text": "360",
        "alias": "number",
        "meta": "@sys.number",
        "userDefined": false
      },
      {
        "text": " track ?",
        "userDefined": false
      }
    ],
    "isTemplate": false,
    "count": 0,
    "updated": 1541188836
  },
  {
    "id": "7e92b691-f232-4d34-af01-be65a7bf4b06",
    "data": [
      {
        "text": "Who is the track chair for the career 360 track?",
        "userDefined": false
      }
    ],
    "isTemplate": false,
    "count": 0,
    "updated": 1539220148
  }
]