[
  {
    "id": "9857c295-ca36-4f7f-ae12-b59ec0775b71",
    "data": [
      {
        "text": "smartcity ecity",
        "userDefined": false
      }
    ],
    "isTemplate": false,
    "count": 0,
    "updated": 1541434577
  },
  {
    "id": "529c9ce1-c32f-428d-b773-fdc5a72a393d",
    "data": [
      {
        "text": "Technology for Better Quality of Life",
        "userDefined": false
      }
    ],
    "isTemplate": false,
    "count": 0,
    "updated": 1541434577
  },
  {
    "id": "6dd7c138-a57a-4969-9482-4b6d6762706e",
    "data": [
      {
        "text": "Ecity",
        "userDefined": false
      }
    ],
    "isTemplate": false,
    "count": 0,
    "updated": 1541434577
  },
  {
    "id": "5b4c108d-3712-40ae-92cc-608209eed86a",
    "data": [
      {
        "text": "Smart City",
        "userDefined": false
      }
    ],
    "isTemplate": false,
    "count": 0,
    "updated": 1541434577
  },
  {
    "id": "e5b15759-59e5-42e7-93cb-38ea296f4cc5",
    "data": [
      {
        "text": "SmartCity@Ecity - Technology for Better Quality of Life",
        "userDefined": false
      }
    ],
    "isTemplate": false,
    "count": 0,
    "updated": 1540486210
  }
]