[
  {
    "id": "08f26f41-f723-44d2-857c-6a229afb1158",
    "data": [
      {
        "text": "Rising design in technology",
        "userDefined": false
      }
    ],
    "isTemplate": false,
    "count": 0,
    "updated": 1541179290
  },
  {
    "id": "01ea8462-5f4e-4f3b-b4e6-29424d21cf5d",
    "data": [
      {
        "text": "Design in Technology",
        "userDefined": false
      }
    ],
    "isTemplate": false,
    "count": 0,
    "updated": 1541179290
  },
  {
    "id": "f020ff06-cf3a-4be6-ba49-89a138d84e0e",
    "data": [
      {
        "text": "The Rising Role of Design",
        "userDefined": false
      }
    ],
    "isTemplate": false,
    "count": 0,
    "updated": 1541179290
  },
  {
    "id": "4f7e021e-7ca6-4ba4-9890-e653cb1330c4",
    "data": [
      {
        "text": "16 November",
        "alias": "date",
        "meta": "@sys.date",
        "userDefined": false
      },
      {
        "text": " The Rising Role of Design in Technology",
        "userDefined": false
      }
    ],
    "isTemplate": false,
    "count": 0,
    "updated": 1541179290
  },
  {
    "id": "c858cbaf-a4b9-4dcb-afc9-1515ac5e0326",
    "data": [
      {
        "text": "The Rising Role of Design in Technology",
        "userDefined": false
      }
    ],
    "isTemplate": false,
    "count": 0,
    "updated": 1540477445
  }
]